odoo8_addon_pos_payment_terminal-8.0.0.1.0.99.dev15-py3.8-nspkg.pth
odoo_addons/pos_payment_terminal/README.rst
odoo_addons/pos_payment_terminal/__init__.py
odoo_addons/pos_payment_terminal/__openerp__.py
odoo_addons/pos_payment_terminal/pos_payment_terminal.py
odoo_addons/pos_payment_terminal/pos_payment_terminal.xml
odoo_addons/pos_payment_terminal/pos_payment_terminal_demo.xml
odoo_addons/pos_payment_terminal/pos_payment_terminal_view.xml
odoo_addons/pos_payment_terminal/i18n/ar.po
odoo_addons/pos_payment_terminal/i18n/bs.po
odoo_addons/pos_payment_terminal/i18n/ca.po
odoo_addons/pos_payment_terminal/i18n/ca_ES.po
odoo_addons/pos_payment_terminal/i18n/cs.po
odoo_addons/pos_payment_terminal/i18n/da.po
odoo_addons/pos_payment_terminal/i18n/de.po
odoo_addons/pos_payment_terminal/i18n/en_GB.po
odoo_addons/pos_payment_terminal/i18n/es.po
odoo_addons/pos_payment_terminal/i18n/es_CR.po
odoo_addons/pos_payment_terminal/i18n/es_EC.po
odoo_addons/pos_payment_terminal/i18n/es_ES.po
odoo_addons/pos_payment_terminal/i18n/es_MX.po
odoo_addons/pos_payment_terminal/i18n/es_VE.po
odoo_addons/pos_payment_terminal/i18n/et.po
odoo_addons/pos_payment_terminal/i18n/fi.po
odoo_addons/pos_payment_terminal/i18n/fr.po
odoo_addons/pos_payment_terminal/i18n/gl.po
odoo_addons/pos_payment_terminal/i18n/hr.po
odoo_addons/pos_payment_terminal/i18n/hr_HR.po
odoo_addons/pos_payment_terminal/i18n/hu.po
odoo_addons/pos_payment_terminal/i18n/id.po
odoo_addons/pos_payment_terminal/i18n/it.po
odoo_addons/pos_payment_terminal/i18n/ja.po
odoo_addons/pos_payment_terminal/i18n/lt.po
odoo_addons/pos_payment_terminal/i18n/lt_LT.po
odoo_addons/pos_payment_terminal/i18n/mk.po
odoo_addons/pos_payment_terminal/i18n/mn.po
odoo_addons/pos_payment_terminal/i18n/nb.po
odoo_addons/pos_payment_terminal/i18n/nb_NO.po
odoo_addons/pos_payment_terminal/i18n/nl.po
odoo_addons/pos_payment_terminal/i18n/nl_BE.po
odoo_addons/pos_payment_terminal/i18n/pl.po
odoo_addons/pos_payment_terminal/i18n/pos_payment_terminal.pot
odoo8_addon_pos_payment_terminal-8.0.0.1.0.99.dev15.dist-info/METADATA
odoo8_addon_pos_payment_terminal-8.0.0.1.0.99.dev15.dist-info/WHEEL
odoo8_addon_pos_payment_terminal-8.0.0.1.0.99.dev15.dist-info/namespace_packages.txt
odoo8_addon_pos_payment_terminal-8.0.0.1.0.99.dev15.dist-info/top_level.txt
odoo8_addon_pos_payment_terminal-8.0.0.1.0.99.dev15.dist-info/RECORD
